odoo/addons/mail_debranding/README.rst
odoo/addons/mail_debranding/__init__.py
odoo/addons/mail_debranding/__manifest__.py
odoo/addons/mail_debranding/i18n/de.po
odoo/addons/mail_debranding/i18n/es.po
odoo/addons/mail_debranding/i18n/fr.po
odoo/addons/mail_debranding/i18n/fr_FR.po
odoo/addons/mail_debranding/i18n/it.po
odoo/addons/mail_debranding/i18n/mail_debrand.pot
odoo/addons/mail_debranding/i18n/mail_debranding.pot
odoo/addons/mail_debranding/i18n/nl.po
odoo/addons/mail_debranding/i18n/pt.po
odoo/addons/mail_debranding/i18n/sl.po
odoo/addons/mail_debranding/i18n/sr_Latn.po
odoo/addons/mail_debranding/i18n/sv.po
odoo/addons/mail_debranding/i18n/tr.po
odoo/addons/mail_debranding/models/__init__.py
odoo/addons/mail_debranding/models/mail_mail.py
odoo/addons/mail_debranding/models/mail_render_mixin.py
odoo/addons/mail_debranding/readme/CONTRIBUTORS.md
odoo/addons/mail_debranding/readme/DESCRIPTION.md
odoo/addons/mail_debranding/readme/HISTORY.md
odoo/addons/mail_debranding/readme/ROADMAP.md
odoo/addons/mail_debranding/readme/USAGE.md
odoo/addons/mail_debranding/static/description/icon.png
odoo/addons/mail_debranding/static/description/icon.svg
odoo/addons/mail_debranding/static/description/index.html
odoo/addons/mail_debranding/tests/__init__.py
odoo/addons/mail_debranding/tests/test_mail_debrand.py
odoo/addons/mail_debranding/tests/test_mail_debrand_digest.py
odoo/addons/mail_debranding/tests/test_mail_debrand_signup.py
odoo_addon_mail_debranding-19.0.1.0.0.5.dist-info/METADATA
odoo_addon_mail_debranding-19.0.1.0.0.5.dist-info/WHEEL
odoo_addon_mail_debranding-19.0.1.0.0.5.dist-info/top_level.txt
odoo_addon_mail_debranding-19.0.1.0.0.5.dist-info/RECORD
