Metadata-Version: 2.1
Name: odoo-addon-mail_debranding
Version: 19.0.1.0.0.5
Requires-Dist: odoo==19.0.*
Summary: Remove Odoo branding in sent emails Removes anchor <a href odoo.com togheder with it's parent ( for powerd by) form all the templates removes any 'odoo' that are in tempalte texts > 20characters
Home-page: https://github.com/OCA/server-brand
License: AGPL-3
Author: Tecnativa, ForgeFlow, Onestein, Sodexis, Nexterp Romania, Odoo Community Association (OCA)
Author-email: support@odoo-community.org
Classifier: Programming Language :: Python
Classifier: Framework :: Odoo
Classifier: Framework :: Odoo :: 19.0
Classifier: License :: OSI Approved :: GNU Affero General Public License v3
Classifier: Development Status :: 5 - Production/Stable
